docx_asn1/__init__.py
docx_asn1/__main__.py
docx_asn1/utils.py
docx_asn1-1.1.0.dist-info/licenses/LICENSE
docx_asn1-1.1.0.dist-info/METADATA
docx_asn1-1.1.0.dist-info/WHEEL
docx_asn1-1.1.0.dist-info/top_level.txt
docx_asn1-1.1.0.dist-info/RECORD
