Metadata-Version: 2.4
Name: docx-asn1
Version: 1.1.0
Summary: Extract ASN.1 from DOCX files
Author-email: n4n5 <its.just.n4n5@gmail.com>
License: MIT License
Project-URL: Homepage, https://github.com/its-just-nans/docx-asn1
Project-URL: Bug Tracker, https://github.com/its-just-nans/docx-asn1/issues
Keywords: asn1,docx,extract,asn1tools,3gpp
Classifier: License :: OSI Approved :: MIT License
Classifier: Programming Language :: Python
Classifier: Programming Language :: Python :: 3
Requires-Python: >=3.6
License-File: LICENSE
Requires-Dist: python-docx
Dynamic: license-file
